setup.py
PyMeetupJan.egg-info/PKG-INFO
PyMeetupJan.egg-info/SOURCES.txt
PyMeetupJan.egg-info/dependency_links.txt
PyMeetupJan.egg-info/entry_points.txt
PyMeetupJan.egg-info/requires.txt
PyMeetupJan.egg-info/top_level.txt
module_a/__init__.py
module_a/setup_db.py
module_a/tests/__init__.py
module_a/tests/test_setup_db.py
module_b/__init__.py