Metadata-Version: 1.0
Name: PyMeetupJan
Version: 0.1
Summary: Python Nairobi Meetup Package
Home-page: UNKNOWN
Author: Larry Weya
Author-email: larryweya@gmail.com
License: MIT
Keywords: hello world example examples
Platform: UNKNOWN
